{"keywords": [{"value": "Baseball", "rank": "1", "is_major": "N", "name": "subject"}, {"value": "Chicago Cubs", "rank": "2", "is_major": "N", "name": "organizations"}, {"value": "New York Mets", "rank": "3", "is_major": "N", "name": "organizations"}], "headline": {"main": "CUBS\u2019 DREAMS DASHED IN LOSS TO METROPOLITANS; PRAYERS OF WRIGLEY FAITHFUL GO UNANSWERED"}, "byline": [], "web_url": "http://www.nytimes.com/interactive/2015/10/22/sports/baseball/barrymets-layout.html", "source": "The New York Times", "subsection_name": "Baseball", "slideshow_credits": null, "type_of_material": "Interactive Feature", "_id": "5629964c38f0d843c6275e76", "multimedia": [{"height": 126, "subtype": "wide", "legacy": {"widewidth": "190", "wideheight": "126", "wide": "images/2015/10/22/sports/baseball/barrymets-layout/barrymets-layout-thumbWide.jpg"}, "type": "image", "width": 190, "url": "images/2015/10/22/sports/baseball/barrymets-layout/barrymets-layout-thumbWide.jpg"}, {"height": 1080, "subtype": "xlarge", "legacy": {"xlargeheight": "1080", "xlargewidth": "600", "xlarge": "images/2015/10/22/sports/baseball/barrymets-layout/barrymets-layout-articleLarge.jpg"}, "type": "image", "width": 600, "url": "images/2015/10/22/sports/baseball/barrymets-layout/barrymets-layout-articleLarge.jpg"}, {"height": 75, "subtype": "thumbnail", "legacy": {"thumbnailwidth": "75", "thumbnailheight": "75", "thumbnail": "images/2015/10/22/sports/baseball/barrymets-layout/barrymets-layout-thumbStandard.jpg"}, "type": "image", "width": 75, "url": "images/2015/10/22/sports/baseball/barrymets-layout/barrymets-layout-thumbStandard.jpg"}], "pub_date": "2015-10-22T00:00:00Z", "print_page": null, "section_name": "Sports", "word_count": null, "blog": [], "news_desk": "Sports / Baseball", "snippet": "Dispatch from Chicago, 107-year-late edition", "document_type": "multimedia", "abstract": null, "lead_paragraph": "Dispatch from Chicago, 107-year-late edition"}