{"document_type": "article", "snippet": "IBM and Harley-Davidson shares were down after their quarterly reports disappointed investors.", "type_of_material": "News", "web_url": "http://www.nytimes.com/2015/10/21/business/daily-stock-market-activity.html", "subsection_name": null, "blog": [], "section_name": "Business Day", "source": "The New York Times", "pub_date": "2015-10-21T00:00:00Z", "word_count": "758", "slideshow_credits": null, "news_desk": "Business", "byline": {"original": "By THE ASSOCIATED PRESS", "person": [], "organization": "THE ASSOCIATED PRESS"}, "abstract": "Three-day winning streak in United States stock market ends due to weak company reports and projections.", "keywords": [{"value": "Stocks and Bonds", "rank": "1", "name": "subject", "is_major": "Y"}, {"value": "Nasdaq Composite Index", "rank": "2", "name": "subject", "is_major": "N"}, {"value": "Standard & Poor's 500-Stock Index", "rank": "3", "name": "subject", "is_major": "N"}, {"value": "Dow Jones Stock Average", "rank": "4", "name": "subject", "is_major": "N"}], "print_page": "10", "multimedia": [], "lead_paragraph": "IBM and Harley-Davidson shares were down after their quarterly reports disappointed investors.", "headline": {"print_headline": "Market Declines Slightly as Investors Decode Earnings at U.S. Corporations", "main": "Market Lower as Some Companies Report Weak Earnings"}, "_id": "5626474c38f0d837bee93c8a"}