{"keywords": [{"value": "Bribery and Kickbacks", "rank": "1", "is_major": "Y", "name": "subject"}, {"value": "Presidential Election of 2012", "rank": "2", "is_major": "Y", "name": "subject"}, {"value": "Paul, Ron", "rank": "3", "is_major": "Y", "name": "persons"}, {"value": "Campaign Finance", "rank": "4", "is_major": "Y", "name": "subject"}, {"value": "Iowa", "rank": "6", "is_major": "N", "name": "glocations"}], "headline": {"print_headline": "Iowa: Charges Dropped Against One Ron Paul Aide ", "content_kicker": "National Briefing | Midwest", "main": "Iowa: Charges Dropped Against One Ron Paul Aide "}, "byline": {"contributor": "", "organization": "THE ASSOCIATED PRESS", "original": "By THE ASSOCIATED PRESS", "person": []}, "web_url": "http://www.nytimes.com/2015/10/10/us/politics/iowa-charges-dropped-against-one-ron-paul-aide.html", "source": "The New York Times", "subsection_name": null, "slideshow_credits": null, "type_of_material": "Brief", "_id": "56186f4538f0d814e1370401", "multimedia": [], "pub_date": "2015-10-10T00:00:00Z", "print_page": "14", "section_name": "U.S.", "word_count": "159", "blog": [], "news_desk": "National", "snippet": "A federal judge dismissed charges Friday against Ron Paul\u2019s 2012 presidential campaign manager.", "document_type": "article", "abstract": "Judge John Jarvey dismisses charges against John Tate, Ron Paul's 2012 presidential campaign manager, alleging that he bribed former Iowa Sen Kent Sorenson for his endorsement; charges remain against aides Jesse Benton and Dimitri Kesari.", "lead_paragraph": "A federal judge dismissed charges Friday against Ron Paul\u2019s 2012 presidential campaign manager."}