{"keywords": [{"value": "Yasukuni Shrine (Tokyo, Japan)", "rank": "1", "is_major": "N", "name": "organizations"}, {"value": "Tokyo (Japan)", "rank": "2", "is_major": "N", "name": "glocations"}], "headline": {"main": "Japanese Lawmakers Visit Tokyo Shrine"}, "byline": {"organization": "REUTERS", "original": "By REUTERS", "person": []}, "web_url": "http://www.nytimes.com/video/world/asia/100000003987383/japanese-lawmakers-visit-tokyo-shrine.html", "source": "The New York Times", "subsection_name": "Asia Pacific", "slideshow_credits": null, "type_of_material": "Video", "_id": "5626193238f0d837bee93bdd", "multimedia": [{"height": 126, "subtype": "wide", "legacy": {"widewidth": "190", "wideheight": "126", "wide": "images/2015/10/20/multimedia/japan-yasukuni/japan-yasukuni-thumbWide.jpg"}, "type": "image", "width": 190, "url": "images/2015/10/20/multimedia/japan-yasukuni/japan-yasukuni-thumbWide.jpg"}, {"height": 412, "subtype": "xlarge", "legacy": {"xlargeheight": "412", "xlargewidth": "600", "xlarge": "images/2015/10/20/multimedia/japan-yasukuni/japan-yasukuni-articleLarge.jpg"}, "type": "image", "width": 600, "url": "images/2015/10/20/multimedia/japan-yasukuni/japan-yasukuni-articleLarge.jpg"}, {"height": 75, "subtype": "thumbnail", "legacy": {"thumbnailwidth": "75", "thumbnailheight": "75", "thumbnail": "images/2015/10/20/multimedia/japan-yasukuni/japan-yasukuni-thumbStandard.jpg"}, "type": "image", "width": 75, "url": "images/2015/10/20/multimedia/japan-yasukuni/japan-yasukuni-thumbStandard.jpg"}], "pub_date": "2015-10-20T06:36:15Z", "print_page": null, "section_name": "World", "word_count": "20", "blog": [], "news_desk": "World / Asia Pacific", "snippet": "Dozens of lawmakers visited the Yasukuni shrine in Tokyo on Tuesday. The shrine commemorates Japan\u2019s war dead, including war criminals.", "document_type": "multimedia", "abstract": null, "lead_paragraph": "Dozens of lawmakers visited the Yasukuni shrine in Tokyo on Tuesday. The shrine commemorates Japan\u2019s war dead, including war criminals."}