{"document_type": "article", "snippet": "The man, Abdurraouf Eshati, 29, had been linked to a planned $28.5 million deal to send 1,100 tons of ammunition to Libya via Italy.", "type_of_material": "Brief", "web_url": "http://www.nytimes.com/2015/10/28/world/europe/britain-man-is-sentenced-in-plan-to-arm-libyans.html", "subsection_name": "Europe", "blog": [], "section_name": "World", "source": "The New York Times", "pub_date": "2015-10-28T00:00:00Z", "word_count": "72", "slideshow_credits": null, "news_desk": "Foreign", "byline": {"original": "By THE ASSOCIATED PRESS", "person": [], "organization": "THE ASSOCIATED PRESS"}, "abstract": null, "keywords": [{"value": "Libya", "rank": "1", "name": "glocations", "is_major": "N"}, {"value": "Eshati, Abdurraouf", "rank": "2", "name": "persons", "is_major": "N"}, {"value": "Terrorism", "rank": "3", "name": "subject", "is_major": "N"}, {"value": "Great Britain", "rank": "4", "name": "glocations", "is_major": "N"}, {"value": "Arms Trade", "rank": "5", "name": "subject", "is_major": "N"}], "print_page": "", "multimedia": [], "lead_paragraph": "The man, Abdurraouf Eshati, 29, had been linked to a planned $28.5 million deal to send 1,100 tons of ammunition to Libya via Italy.", "headline": {"content_kicker": "World Briefing", "print_headline": "Britain: Man Is Sentenced in Plan to Arm Libyans", "main": "Britain: Man Is Sentenced in Plan to Arm Libyans"}, "_id": "563024aa38f0d8595b45cb56"}