{"document_type": "article", "snippet": "Mr. Abrams was the first person hired by Berry Gordy Jr., the founder of Motown, before the company officially existed.", "type_of_material": "Obituary", "web_url": "http://www.nytimes.com/2015/10/05/arts/music/al-abrams-motown-records-first-publicist-dies-at-74.html", "subsection_name": "Music", "blog": [], "section_name": "Arts", "source": "The New York Times", "pub_date": "2015-10-05T00:00:00Z", "word_count": "261", "slideshow_credits": null, "news_desk": "Culture", "byline": {"person": [], "contributor": "", "organization": "THE ASSOCIATED PRESS", "original": "By THE ASSOCIATED PRESS"}, "abstract": "Al Abrams, original press officer and publicist for Motown Records, dies at age 74.   ", "keywords": [{"value": "Deaths (Obituaries)", "rank": "1", "name": "subject", "is_major": "Y"}, {"value": "Motown Records", "rank": "2", "name": "organizations", "is_major": "N"}, {"value": "Public Relations and Publicity", "rank": "3", "name": "subject", "is_major": "N"}, {"value": "Abrams, Al (1941-2015)", "rank": "4", "name": "persons", "is_major": "N"}], "print_page": "11", "multimedia": [{"subtype": "wide", "legacy": {"wideheight": "126", "wide": "images/2015/10/05/arts/abrams-obit/abrams-obit-thumbWide-v3.jpg", "widewidth": "190"}, "type": "image", "width": 190, "height": 126, "url": "images/2015/10/05/arts/abrams-obit/abrams-obit-thumbWide-v3.jpg"}, {"subtype": "xlarge", "legacy": {"xlargeheight": "400", "xlargewidth": "600", "xlarge": "images/2015/10/05/arts/abrams-obit/abrams-obit-articleLarge-v3.jpg"}, "type": "image", "width": 600, "height": 400, "url": "images/2015/10/05/arts/abrams-obit/abrams-obit-articleLarge-v3.jpg"}, {"subtype": "thumbnail", "legacy": {"thumbnail": "images/2015/10/05/arts/abrams-obit/abrams-obit-thumbStandard.jpg", "thumbnailheight": "75", "thumbnailwidth": "75"}, "type": "image", "width": 75, "height": 75, "url": "images/2015/10/05/arts/abrams-obit/abrams-obit-thumbStandard.jpg"}], "lead_paragraph": "Mr. Abrams was the first person hired by Berry Gordy Jr., the founder of Motown, before the company officially existed.", "headline": {"print_headline": "Al Abrams, 74, Motown Records&#8217; First Publicist ", "main": "Al Abrams, Motown Records&#8217; First Publicist, Dies at 74"}, "_id": "5611d49738f0d86550b965c7"}