{"keywords": [{"value": "Soccer", "rank": "1", "is_major": "Y", "name": "subject"}, {"value": "UEFA Champions League (Soccer)", "rank": "2", "is_major": "N", "name": "subject"}, {"value": "Arsenal (Soccer Team)", "rank": "3", "is_major": "Y", "name": "organizations"}, {"value": "Bayern Munich (Soccer Team)", "rank": "4", "is_major": "Y", "name": "organizations"}], "headline": {"print_headline": "Arsenal Gets Needed Win", "content_kicker": "Sports Briefing | Soccer", "main": "Arsenal Gets a Needed Win Over Bayern Munich"}, "byline": {"contributor": "", "organization": "THE ASSOCIATED PRESS", "original": "By THE ASSOCIATED PRESS", "person": []}, "web_url": "http://www.nytimes.com/2015/10/21/sports/soccer/arsenal-gets-a-needed-win-over-bayern-munich.html", "source": "The New York Times", "subsection_name": "Soccer", "slideshow_credits": null, "type_of_material": "Brief", "_id": "5627057c38f0d85d3d8b36e9", "multimedia": [], "pub_date": "2015-10-21T00:00:00Z", "print_page": "16", "section_name": "Sports", "word_count": "162", "blog": [], "news_desk": "Sports", "snippet": "Arsenal remains at the bottom of Group F in the Champions League.", "document_type": "article", "abstract": "Arsenal defeats Bayern Munich, 2-0, in Champions League; other soccer news noted.", "lead_paragraph": "Arsenal remains at the bottom of Group F in the Champions League."}