{"document_type": "article", "snippet": "Ohio State Coach Urban Meyer said he was not ready to publicly name a starting quarterback for the top-ranked Buckeyes\u2019 game at Rutgers on Saturday.", "type_of_material": "Brief", "web_url": "http://www.nytimes.com/2015/10/20/sports/ncaafootball/buckeyes-set-to-pick-starter.html", "subsection_name": "College Football", "blog": [], "section_name": "Sports", "source": "The New York Times", "pub_date": "2015-10-20T00:00:00Z", "word_count": "60", "slideshow_credits": null, "news_desk": "Sports", "byline": {"original": "By THE ASSOCIATED PRESS", "person": [], "organization": "THE ASSOCIATED PRESS"}, "abstract": null, "keywords": [{"value": "Football (College)", "rank": "1", "name": "subject", "is_major": "N"}, {"value": "Ohio State University", "rank": "2", "name": "organizations", "is_major": "N"}, {"value": "Barrett, J T (1995- )", "rank": "3", "name": "persons", "is_major": "N"}], "print_page": "", "multimedia": [], "lead_paragraph": "Ohio State Coach Urban Meyer said he was not ready to publicly name a starting quarterback for the top-ranked Buckeyes\u2019 game at Rutgers on Saturday.", "headline": {"print_headline": "Buckeyes Set to Pick Starter", "main": "Buckeyes Set to Pick Starter"}, "_id": "5625ebaa38f0d837bee93ae4"}