{"document_type": "article", "snippet": "A giraffe born at a central California zoo last month died Sunday after running into a fence.", "type_of_material": "Brief", "web_url": "http://www.nytimes.com/2015/10/13/us/california-baby-giraffe-is-killed.html", "subsection_name": null, "blog": [], "section_name": "U.S.", "source": "The New York Times", "pub_date": "2015-10-13T00:00:00Z", "word_count": "48", "slideshow_credits": null, "news_desk": "National", "byline": {"person": [], "contributor": "", "organization": "THE ASSOCIATED PRESS", "original": "By THE ASSOCIATED PRESS"}, "abstract": "Baby giraffe dies after running into fence during preview event at Chaffee Zoo, California.", "keywords": [{"value": "Zoos", "rank": "1", "name": "subject", "is_major": "Y"}, {"value": "Giraffes", "rank": "2", "name": "subject", "is_major": "Y"}, {"value": "California", "rank": "3", "name": "glocations", "is_major": "Y"}], "print_page": "14", "multimedia": [], "lead_paragraph": "A giraffe born at a central California zoo last month died Sunday after running into a fence.", "headline": {"content_kicker": "National Briefing | West", "print_headline": "California: Baby Giraffe Is Killed ", "main": "California: Baby Giraffe Is Killed "}, "_id": "561c56bc38f0d84d2f3b8ace"}