{"document_type": "multimedia", "snippet": "The pastor of a Singapore megachurch, who was convicted of fraud on Wednesday, arrived at court with his wife, whose pop music career he used millions in church funds to promote.", "type_of_material": "Video", "web_url": "http://www.nytimes.com/video/world/asia/100000003990387/court-finds-pastor-used-funds-for-wife.html", "subsection_name": "Asia Pacific", "blog": [], "section_name": "World", "source": "The New York Times", "pub_date": "2015-10-21T12:14:12Z", "word_count": "31", "slideshow_credits": null, "news_desk": "World / Asia Pacific", "byline": {"original": "By THE ASSOCIATED PRESS", "person": [], "organization": "THE ASSOCIATED PRESS"}, "abstract": null, "keywords": [{"value": "Singapore", "rank": "1", "name": "glocations", "is_major": "N"}], "print_page": null, "multimedia": [{"subtype": "wide", "legacy": {"wideheight": "126", "wide": "images/2015/10/22/world/asia/22singapore/22singapore-thumbWide.jpg", "widewidth": "190"}, "type": "image", "width": 190, "height": 126, "url": "images/2015/10/22/world/asia/22singapore/22singapore-thumbWide.jpg"}, {"subtype": "xlarge", "legacy": {"xlargeheight": "413", "xlargewidth": "600", "xlarge": "images/2015/10/22/world/asia/22singapore/22singapore-articleLarge.jpg"}, "type": "image", "width": 600, "height": 413, "url": "images/2015/10/22/world/asia/22singapore/22singapore-articleLarge.jpg"}, {"subtype": "thumbnail", "legacy": {"thumbnail": "images/2015/10/22/world/asia/22singapore/22singapore-thumbStandard.jpg", "thumbnailheight": "75", "thumbnailwidth": "75"}, "type": "image", "width": 75, "height": 75, "url": "images/2015/10/22/world/asia/22singapore/22singapore-thumbStandard.jpg"}], "lead_paragraph": "The pastor of a Singapore megachurch, who was convicted of fraud on Wednesday, arrived at court with his wife, whose pop music career he used millions in church funds to promote.", "headline": {"main": "Court Finds Pastor Used Funds for Wife"}, "_id": "5627b9ed38f0d80f1ae08a19"}