{"keywords": [{"value": "Nobel Prizes", "rank": "1", "is_major": "N", "name": "subject"}, {"value": "Tunisia", "rank": "2", "is_major": "N", "name": "glocations"}], "headline": {"main": "2015 Nobel Peace Prize Awarded"}, "byline": {"organization": "THE ASSOCIATED PRESS", "original": "By THE ASSOCIATED PRESS", "person": []}, "web_url": "http://www.nytimes.com/video/world/africa/100000003967967/2015-nobel-peace-prize-awarded.html", "source": "The New York Times", "subsection_name": "Africa", "slideshow_credits": null, "type_of_material": "Video", "_id": "5617954a38f0d8690d4ba200", "multimedia": [{"height": 126, "subtype": "wide", "legacy": {"widewidth": "190", "wideheight": "126", "wide": "images/2015/10/10/world/middleeast/10Nobel2-web/10Nobel2-web-thumbWide.jpg"}, "type": "image", "width": 190, "url": "images/2015/10/10/world/middleeast/10Nobel2-web/10Nobel2-web-thumbWide.jpg"}, {"height": 400, "subtype": "xlarge", "legacy": {"xlargeheight": "400", "xlargewidth": "600", "xlarge": "images/2015/10/10/world/middleeast/10Nobel2-web/10Nobel2-web-articleLarge.jpg"}, "type": "image", "width": 600, "url": "images/2015/10/10/world/middleeast/10Nobel2-web/10Nobel2-web-articleLarge.jpg"}, {"height": 75, "subtype": "thumbnail", "legacy": {"thumbnailwidth": "75", "thumbnailheight": "75", "thumbnail": "images/2015/10/10/world/middleeast/10Nobel2-web/10Nobel2-web-thumbStandard.jpg"}, "type": "image", "width": 75, "url": "images/2015/10/10/world/middleeast/10Nobel2-web/10Nobel2-web-thumbStandard.jpg"}], "pub_date": "2015-10-09T06:21:31Z", "print_page": null, "section_name": "World", "word_count": "32", "blog": [], "news_desk": "World / Africa", "snippet": "Tunisia\u2019s National Dialogue Quartet won the 2015 Nobel Peace Prize for \u201cits decisive contribution to the building of a pluralistic democracy in Tunisia in the wake of the Jasmine Revolution of 2011.\u201d", "document_type": "multimedia", "abstract": null, "lead_paragraph": "Tunisia\u2019s National Dialogue Quartet won the 2015 Nobel Peace Prize for \u201cits decisive contribution to the building of a pluralistic democracy in Tunisia in the wake of the Jasmine Revolution of 2011.\u201d"}