{"keywords": [{"value": "Trans-Pacific Partnership", "rank": "1", "is_major": "N", "name": "subject"}, {"value": "Froman, Michael B", "rank": "2", "is_major": "N", "name": "persons"}, {"value": "Abe, Shinzo", "rank": "3", "is_major": "N", "name": "persons"}, {"value": "Japan", "rank": "4", "is_major": "N", "name": "glocations"}], "headline": {"main": "World Leaders React to Trade Agreement"}, "byline": {"organization": "REUTERS", "original": "By REUTERS", "person": []}, "web_url": "http://www.nytimes.com/video/world/americas/100000003958236/world-leaders-react-to-trade-agreement.html", "source": "The New York Times", "subsection_name": "Americas", "slideshow_credits": null, "type_of_material": "Video", "_id": "56129fae38f0d87a71faa0cf", "multimedia": [{"height": 126, "subtype": "wide", "legacy": {"widewidth": "190", "wideheight": "126", "wide": "images/2015/10/05/multimedia/trans-pacific-conf/trans-pacific-conf-thumbWide.jpg"}, "type": "image", "width": 190, "url": "images/2015/10/05/multimedia/trans-pacific-conf/trans-pacific-conf-thumbWide.jpg"}, {"height": 338, "subtype": "xlarge", "legacy": {"xlargeheight": "338", "xlargewidth": "600", "xlarge": "images/2015/10/05/multimedia/trans-pacific-conf/trans-pacific-conf-articleLarge.jpg"}, "type": "image", "width": 600, "url": "images/2015/10/05/multimedia/trans-pacific-conf/trans-pacific-conf-articleLarge.jpg"}, {"height": 75, "subtype": "thumbnail", "legacy": {"thumbnailwidth": "75", "thumbnailheight": "75", "thumbnail": "images/2015/10/05/multimedia/trans-pacific-conf/trans-pacific-conf-thumbStandard.jpg"}, "type": "image", "width": 75, "url": "images/2015/10/05/multimedia/trans-pacific-conf/trans-pacific-conf-thumbStandard.jpg"}], "pub_date": "2015-10-05T12:04:30Z", "print_page": null, "section_name": "World", "word_count": "20", "blog": [], "news_desk": "World / Americas", "snippet": "The United States trade representative, Michael Froman, and Prime Minister Shinzo Abe of Japan discuss the Trans-Pacific Partnership trade deal.", "document_type": "multimedia", "abstract": null, "lead_paragraph": "The United States trade representative, Michael Froman, and Prime Minister Shinzo Abe of Japan discuss the Trans-Pacific Partnership trade deal."}