{"document_type": "article", "snippet": "The couple were married Saturday at the Quechee Inn in Quechee, Vt.", "type_of_material": "News", "web_url": "http://www.nytimes.com/2015/10/18/fashion/weddings/hannah-goldfield-joshua-stern.html", "subsection_name": "Weddings", "blog": [], "section_name": "Fashion & Style", "source": "The New York Times", "pub_date": "2015-10-18T00:00:00Z", "word_count": "127", "slideshow_credits": null, "news_desk": "Society", "byline": [], "abstract": null, "keywords": [{"value": "Weddings and Engagements", "rank": "1", "name": "subject", "is_major": "N"}], "print_page": "18", "multimedia": [{"subtype": "wide", "legacy": {"wideheight": "126", "wide": "images/2015/10/18/fashion/weddings/18GOLDFIELDjpg/18GOLDFIELDjpg-thumbWide-v2.jpg", "widewidth": "190"}, "type": "image", "width": 190, "height": 126, "url": "images/2015/10/18/fashion/weddings/18GOLDFIELDjpg/18GOLDFIELDjpg-thumbWide-v2.jpg"}, {"subtype": "xlarge", "legacy": {"xlargeheight": "355", "xlargewidth": "600", "xlarge": "images/2015/10/18/fashion/weddings/18GOLDFIELDjpg/18GOLDFIELDjpg-articleLarge-v2.jpg"}, "type": "image", "width": 600, "height": 355, "url": "images/2015/10/18/fashion/weddings/18GOLDFIELDjpg/18GOLDFIELDjpg-articleLarge-v2.jpg"}, {"subtype": "thumbnail", "legacy": {"thumbnail": "images/2015/10/18/fashion/weddings/18GOLDFIELDjpg/18GOLDFIELDjpg-thumbStandard.jpg", "thumbnailheight": "75", "thumbnailwidth": "75"}, "type": "image", "width": 75, "height": 75, "url": "images/2015/10/18/fashion/weddings/18GOLDFIELDjpg/18GOLDFIELDjpg-thumbStandard.jpg"}], "lead_paragraph": "The couple were married Saturday at the Quechee Inn in Quechee, Vt.", "headline": {"print_headline": "Hannah Goldfield,  Joshua Stern", "main": "Hannah Goldfield, Joshua Stern"}, "_id": "56231cdf38f0d815e8e113cf"}