{"keywords": [{"value": "Elderly", "rank": "1", "is_major": "N", "name": "subject"}, {"value": "Health Insurance and Managed Care", "rank": "3", "is_major": "N", "name": "subject"}, {"value": "Doctors", "rank": "4", "is_major": "N", "name": "subject"}], "headline": {"kicker": "Letters", "print_headline": "It\u2019s Time for House Calls to Make a Comeback", "content_kicker": "Letters", "main": "It\u2019s Time for Doctors\u2019 House Calls to Make a Comeback"}, "byline": [], "web_url": "http://www.nytimes.com/2015/10/19/opinion/its-time-for-doctors-house-calls-to-make-a-comeback.html", "source": "The New York Times", "subsection_name": null, "slideshow_credits": null, "type_of_material": "Letter", "_id": "5624996a38f0d820b1f6463b", "multimedia": [], "pub_date": "2015-10-19T00:00:00Z", "print_page": "22", "section_name": "Opinion", "word_count": "348", "blog": [], "news_desk": "Letters", "snippet": "The American Academy of Home Care Medicine and a Johns Hopkins geriatrician discuss the many benefits.", "document_type": "article", "abstract": null, "lead_paragraph": "The American Academy of Home Care Medicine and a Johns Hopkins geriatrician discuss the many benefits."}