{"keywords": [{"value": "Voting Machines", "rank": "1", "is_major": "N", "name": "subject"}], "headline": {"kicker": "Letter", "print_headline": "Upgrade Voting Machines", "content_kicker": "Letter", "main": "Upgrade Voting Machines"}, "byline": [], "web_url": "http://www.nytimes.com/2015/10/23/opinion/upgrade-voting-machines.html", "source": "The New York Times", "subsection_name": null, "slideshow_credits": null, "type_of_material": "Letter", "_id": "5629dfe338f0d843c6275f0b", "multimedia": [], "pub_date": "2015-10-23T00:00:00Z", "print_page": "30", "section_name": "Opinion", "word_count": "210", "blog": [], "news_desk": "Letters", "snippet": "An official of an election services company asks why \u201csecure, convenient and inexpensive\u201d voting systems are not being adopted in the United States.", "document_type": "article", "abstract": null, "lead_paragraph": "An official of an election services company asks why \u201csecure, convenient and inexpensive\u201d voting systems are not being adopted in the United States."}